dilithium_py/__init__.py
dilithium_py/dilithium/__init__.py
dilithium_py/dilithium/default_parameters.py
dilithium_py/dilithium/dilithium.py
dilithium_py/drbg/__init__.py
dilithium_py/drbg/aes256_ctr_drbg.py
dilithium_py/ml_dsa/__init__.py
dilithium_py/ml_dsa/default_parameters.py
dilithium_py/ml_dsa/hash_ml_dsa.py
dilithium_py/ml_dsa/ml_dsa.py
dilithium_py/ml_dsa/pkcs.py
dilithium_py/modules/__init__.py
dilithium_py/modules/modules.py
dilithium_py/modules/modules_generic.py
dilithium_py/polynomials/__init__.py
dilithium_py/polynomials/polynomials.py
dilithium_py/polynomials/polynomials_generic.py
dilithium_py/shake/shake_wrapper.py
dilithium_py/utilities/__init__.py
dilithium_py/utilities/utils.py
dilithium_py-1.3.0.dist-info/METADATA
dilithium_py-1.3.0.dist-info/WHEEL
dilithium_py-1.3.0.dist-info/licenses/LICENSE
dilithium_py-1.3.0.dist-info/RECORD
