Metadata-Version: 2.4
Name: dilithium-py
Version: 1.3.0
Summary: A pure python implementation of ML-DSA (FIPS 204)
Project-URL: Homepage, https://github.com/GiacomoPope/dilithium-py
Project-URL: Issues, https://github.com/GiacomoPope/dilithium-py/issues
License-Expression: MIT
License-File: LICENSE
Classifier: Programming Language :: Python :: 3
Classifier: Topic :: Security :: Cryptography
Requires-Python: >=3.9
Provides-Extra: pkcs
Requires-Dist: ecdsa>=0.19.1; extra == 'pkcs'
